{"applianceage":12,"applianceid":"4","energy":"0.034103","uniqueid":"1587412486-32"}
{"applianceage":4,"applianceid":"3","energy":"0.212569","uniqueid":"1587412486-135"}
{"applianceage":23,"applianceid":"5","energy":"0.147975","uniqueid":"1587412486-178"}
{"applianceage":13,"applianceid":"1","energy":"0.184701","uniqueid":"1587412486-292"}
{"applianceage":24,"applianceid":"1","energy":"0.195662","uniqueid":"1587412486-370"}
{"applianceage":4,"applianceid":"3","energy":"0.227911","uniqueid":"1587412486-382"}
{"applianceage":41,"applianceid":"5","energy":"0.141044","uniqueid":"1587412486-444"}
{"applianceage":12,"applianceid":"0","energy":"0.038942","uniqueid":"1587412486-450"}
{"applianceage":23,"applianceid":"2","energy":"0.065684","uniqueid":"1587412486-460"}
{"applianceage":23,"applianceid":"4","energy":"0.02875","uniqueid":"1587412486-485"}
{"applianceage":14,"applianceid":"3","energy":"0.24924","uniqueid":"1587412486-486"}
{"applianceage":11,"applianceid":"5","energy":"0.13674","uniqueid":"1587412486-556"}
{"applianceage":8,"applianceid":"4","energy":"0.026397","uniqueid":"1587412486-564"}
{"applianceage":21,"applianceid":"4","energy":"0.032617","uniqueid":"1587412486-596"}
{"applianceage":14,"applianceid":"2","energy":"0.052827","uniqueid":"1587412486-639"}
{"applianceage":10,"applianceid":"0","energy":"0.03898","uniqueid":"1587412486-661"}
{"applianceage":8,"applianceid":"3","energy":"0.215209","uniqueid":"1587412486-728"}
{"applianceage":12,"applianceid":"4","energy":"0.025204","uniqueid":"1587412486-1003"}
{"applianceage":28,"applianceid":"1","energy":"0.1713","uniqueid":"1587412486-1008"}
{"applianceage":5,"applianceid":"5","energy":"0.133527","uniqueid":"1587412486-1071"}
{"applianceage":38,"applianceid":"0","energy":"0.035825","uniqueid":"1587412486-1167"}
{"applianceage":8,"applianceid":"1","energy":"0.1614","uniqueid":"1587412486-1179"}
{"applianceage":27,"applianceid":"4","energy":"0.028922","uniqueid":"1587412486-1200"}
{"applianceage":32,"applianceid":"3","energy":"0.217265","uniqueid":"1587412486-1402"}
{"applianceage":37,"applianceid":"3","energy":"0.240089","uniqueid":"1587412486-1520"}
{"applianceage":10,"applianceid":"1","energy":"0.156014","uniqueid":"1587412486-1673"}
{"applianceage":15,"applianceid":"4","energy":"0.029353","uniqueid":"1587412486-1840"}
{"applianceage":3,"applianceid":"2","energy":"0.088039","uniqueid":"1587412486-1891"}
{"applianceage":17,"applianceid":"0","energy":"0.049188","uniqueid":"1587412486-1939"}
{"applianceage":28,"applianceid":"2","energy":"0.082579","uniqueid":"1587412486-2088"}
{"applianceage":17,"applianceid":"5","energy":"0.136726","uniqueid":"1587412486-2301"}
{"applianceage":19,"applianceid":"3","energy":"0.203994","uniqueid":"1587412486-2333"}
{"applianceage":20,"applianceid":"4","energy":"0.02129","uniqueid":"1587412486-2343"}
{"applianceage":11,"applianceid":"4","energy":"0.011459","uniqueid":"1587412486-2417"}
{"applianceage":4,"applianceid":"2","energy":"0.050434","uniqueid":"1587412486-2448"}
{"applianceage":20,"applianceid":"3","energy":"0.234372","uniqueid":"1587412486-2458"}
{"applianceage":16,"applianceid":"3","energy":"0.234021","uniqueid":"1587412486-2531"}
{"applianceage":8,"applianceid":"0","energy":"0.039875","uniqueid":"1587412486-2566"}
{"applianceage":29,"applianceid":"5","energy":"0.108221","uniqueid":"1587412486-2646"}
{"applianceage":13,"applianceid":"1","energy":"0.182878","uniqueid":"1587412486-2728"}
{"applianceage":6,"applianceid":"5","energy":"0.135427","uniqueid":"1587412486-2808"}
{"applianceage":27,"applianceid":"2","energy":"0.070242","uniqueid":"1587412486-2839"}
{"applianceage":28,"applianceid":"0","energy":"0.032568","uniqueid":"1587412486-2868"}
{"applianceage":38,"applianceid":"5","energy":"0.102379","uniqueid":"1587412486-3066"}
{"applianceage":16,"applianceid":"0","energy":"0.048237","uniqueid":"1587412486-3123"}
{"applianceage":14,"applianceid":"0","energy":"0.047989","uniqueid":"1587412486-3136"}
{"applianceage":22,"applianceid":"0","energy":"0.043121","uniqueid":"1587412486-3179"}
{"applianceage":22,"applianceid":"5","energy":"0.106946","uniqueid":"1587412486-3296"}
{"applianceage":16,"applianceid":"1","energy":"0.179426","uniqueid":"1587412486-3352"}
{"applianceage":12,"applianceid":"5","energy":"0.105997","uniqueid":"1587412486-3617"}
{"applianceage":23,"applianceid":"0","energy":"0.046858","uniqueid":"1587412486-3718"}
{"applianceage":14,"applianceid":"2","energy":"0.064278","uniqueid":"1587412486-3934"}
{"applianceage":9,"applianceid":"1","energy":"0.164983","uniqueid":"1587412486-4087"}
{"applianceage":6,"applianceid":"2","energy":"0.058901","uniqueid":"1587412486-4268"}
{"applianceage":12,"applianceid":"4","energy":"0.013519","uniqueid":"1587412486-4399"}
{"applianceage":37,"applianceid":"5","energy":"0.147052","uniqueid":"1587412486-4808"}
{"applianceage":14,"applianceid":"1","energy":"0.193875","uniqueid":"1587412486-4895"}
{"applianceage":29,"applianceid":"0","energy":"0.045841","uniqueid":"1587412486-4932"}
{"applianceage":41,"applianceid":"3","energy":"0.245276","uniqueid":"1587412486-5051"}
{"applianceage":24,"applianceid":"0","energy":"0.034756","uniqueid":"1587412486-5146"}
{"applianceage":8,"applianceid":"2","energy":"0.057344","uniqueid":"1587412486-5588"}
{"applianceage":28,"applianceid":"2","energy":"0.085843","uniqueid":"1587412486-5622"}
{"applianceage":18,"applianceid":"5","energy":"0.12648","uniqueid":"1587412486-5698"}
{"applianceage":14,"applianceid":"2","energy":"0.071168","uniqueid":"1587412486-5804"}
{"applianceage":29,"applianceid":"3","energy":"0.232556","uniqueid":"1587412486-5913"}
{"applianceage":4,"applianceid":"4","energy":"0.025753","uniqueid":"1587412486-6018"}
{"applianceage":17,"applianceid":"3","energy":"0.23632","uniqueid":"1587412486-6195"}
{"applianceage":13,"applianceid":"3","energy":"0.246765","uniqueid":"1587412486-6209"}
{"applianceage":45,"applianceid":"0","energy":"0.030534","uniqueid":"1587412486-6270"}
{"applianceage":28,"applianceid":"1","energy":"0.195573","uniqueid":"1587412486-6549"}
{"applianceage":27,"applianceid":"4","energy":"0.039823","uniqueid":"1587412486-6555"}
{"applianceage":21,"applianceid":"5","energy":".108","uniqueid":"1587412486-18806"}
{"applianceage":25,"applianceid":"3","energy":".249","uniqueid":"1587412486-12378"}
{"applianceage":24,"applianceid":"5","energy":".128","uniqueid":"1587412486-19200"}
{"applianceage":29,"applianceid":"1","energy":".182","uniqueid":"1587412486-21167"}
{"applianceage":34,"applianceid":"5","energy":".125","uniqueid":"1587412486-16689"}
{"applianceage":33,"applianceid":"5","energy":".103","uniqueid":"1587412486-19498"}
{"applianceage":42,"applianceid":"0","energy":".051","uniqueid":"1587412486-11376"}
{"applianceage":47,"applianceid":"0","energy":".052","uniqueid":"1587412486-1494"}
{"applianceage":43,"applianceid":"2","energy":".070","uniqueid":"1587412486-4027"}
{"applianceage":43,"applianceid":"3","energy":".249","uniqueid":"1587412486-16230"}
{"applianceage":45,"applianceid":"3","energy":".204","uniqueid":"1587412486-15274"}
